functrace/__init__.py
functrace/api.py
functrace/type_hints.py
functrace/utilities.py
functrace-0.0.5.dist-info/LICENSE
functrace-0.0.5.dist-info/METADATA
functrace-0.0.5.dist-info/WHEEL
functrace-0.0.5.dist-info/top_level.txt
functrace-0.0.5.dist-info/RECORD
