Metadata-Version: 2.1
Name: functrace
Version: 0.0.5
Summary: Python library for tracing function calls and performance
Author: Idan Hazan
License: MIT
Project-URL: homepage, https://pypi.org/project/functrace
Project-URL: repository, https://github.com/idanhazan/functrace
Project-URL: documentation, https://functrace.readthedocs.io
Keywords: trace,tracer,tracing,track,tracker,tracking
Classifier: Development Status :: 4 - Beta
Classifier: Environment :: Console
Classifier: Intended Audience :: Developers
Classifier: License :: OSI Approved :: MIT License
Classifier: Operating System :: OS Independent
Classifier: Programming Language :: Python :: 3
Classifier: Programming Language :: Python :: 3.10
Classifier: Programming Language :: Python :: 3.11
Classifier: Programming Language :: Python :: 3.12
Classifier: Topic :: Software Development :: Debuggers
Classifier: Topic :: Software Development :: Libraries :: Python Modules
Classifier: Topic :: System :: Monitoring
Requires-Python: >=3.10
License-File: LICENSE
